gpt_code_review/__init__.py
gpt_code_review/git_service.py
gpt_code_review/gpt_service.py
gpt_code_review/main.py
tests/__init__.py
tests/test_git_service.py
tests/test_gpt_service.py
tests/test_main.py
gpt_code_review-0.1.3.dist-info/LICENSE
gpt_code_review-0.1.3.dist-info/METADATA
gpt_code_review-0.1.3.dist-info/WHEEL
gpt_code_review-0.1.3.dist-info/entry_points.txt
gpt_code_review-0.1.3.dist-info/top_level.txt
gpt_code_review-0.1.3.dist-info/RECORD
