Metadata-Version: 2.1
Name: gpt-code-review
Version: 0.1.3
Summary: Code review with GPT-3
Home-page: UNKNOWN
Author: Patryk Maruda
Author-email: patrykmaruda@gmail.com
License: UNKNOWN
Platform: UNKNOWN
Requires-Dist: click
Requires-Dist: openai
Requires-Dist: GitPython
